lobster_translator/__init__.py
lobster_translator/helpers.py
lobster_translator/io.py
lobster_translator-0.4.0.dist-info/LICENSE
lobster_translator-0.4.0.dist-info/METADATA
lobster_translator-0.4.0.dist-info/WHEEL
lobster_translator-0.4.0.dist-info/RECORD
